{
  "formatVersion": "1.1",
  "component": {
    "group": "io.github.bootpay",
    "module": "backend",
    "version": "2.2.4",
    "attributes": {
      "org.gradle.status": "release"
    }
  },
  "createdBy": {
    "gradle": {
      "version": "6.8",
      "buildId": "mvybajifivdfvfzqerherbanpi"
    }
  },
  "variants": [
    {
      "name": "apiElements",
      "attributes": {
        "org.gradle.category": "library",
        "org.gradle.dependency.bundling": "external",
        "org.gradle.jvm.version": 8,
        "org.gradle.libraryelements": "jar",
        "org.gradle.usage": "java-api"
      },
      "files": [
        {
          "name": "backend-2.2.4.jar",
          "url": "backend-2.2.4.jar",
          "size": 51204,
          "sha512": "5edfa676eeeca96a7b34c4c51524624ab876fd89e047186afa62267786127f7e367f6925c9f51bf1d2c7e3933d5e34a419c59896448392d1f7bdc426663ca063",
          "sha256": "ff32ce913fc37879aac9b79770480754f07c7ed6183bdec125f335304a0dd0ca",
          "sha1": "0883f62be7d4cd97379ca2540177c5c616641d13",
          "md5": "9a555681a1b298f3c0c8c292c5afbab5"
        }
      ]
    },
    {
      "name": "runtimeElements",
      "attributes": {
        "org.gradle.category": "library",
        "org.gradle.dependency.bundling": "external",
        "org.gradle.jvm.version": 8,
        "org.gradle.libraryelements": "jar",
        "org.gradle.usage": "java-runtime"
      },
      "dependencies": [
        {
          "group": "org.apache.httpcomponents",
          "module": "httpclient",
          "version": {
            "requires": "4.5.13"
          }
        },
        {
          "group": "com.google.code.gson",
          "module": "gson",
          "version": {
            "requires": "2.9.0"
          }
        },
        {
          "group": "commons-io",
          "module": "commons-io",
          "version": {
            "requires": "2.11.0"
          }
        },
        {
          "group": "com.fasterxml.jackson.core",
          "module": "jackson-databind",
          "version": {
            "requires": "2.14.2"
          }
        },
        {
          "group": "com.fasterxml.jackson.core",
          "module": "jackson-core",
          "version": {
            "requires": "2.14.2"
          }
        }
      ],
      "files": [
        {
          "name": "backend-2.2.4.jar",
          "url": "backend-2.2.4.jar",
          "size": 51204,
          "sha512": "5edfa676eeeca96a7b34c4c51524624ab876fd89e047186afa62267786127f7e367f6925c9f51bf1d2c7e3933d5e34a419c59896448392d1f7bdc426663ca063",
          "sha256": "ff32ce913fc37879aac9b79770480754f07c7ed6183bdec125f335304a0dd0ca",
          "sha1": "0883f62be7d4cd97379ca2540177c5c616641d13",
          "md5": "9a555681a1b298f3c0c8c292c5afbab5"
        }
      ]
    },
    {
      "name": "sourcesElements",
      "attributes": {
        "org.gradle.category": "documentation",
        "org.gradle.dependency.bundling": "external",
        "org.gradle.docstype": "sources",
        "org.gradle.usage": "java-runtime"
      },
      "files": [
        {
          "name": "backend-2.2.4-sources.jar",
          "url": "backend-2.2.4-sources.jar",
          "size": 33466,
          "sha512": "e50af8c2704e6a7a88b6b165af735ac7ff6c9f669399c2a42c9ebd2159ca6c8a3765818414b1578f414db19b3d7d0f9c1dd4869a92c36330c2b8ab1ffc838f57",
          "sha256": "db810e88ebc35aa7575811dfa3f682fc8a5a52987a061c6120ded5e35743f7dd",
          "sha1": "aba6856a4614bf519f9869b83d392f8be1be9ab0",
          "md5": "fa755a18763e64211e2b1ea9ec813896"
        }
      ]
    },
    {
      "name": "javadocElements",
      "attributes": {
        "org.gradle.category": "documentation",
        "org.gradle.dependency.bundling": "external",
        "org.gradle.docstype": "javadoc",
        "org.gradle.usage": "java-runtime"
      },
      "files": [
        {
          "name": "backend-2.2.4-javadoc.jar",
          "url": "backend-2.2.4-javadoc.jar",
          "size": 175480,
          "sha512": "8c2889c2cddc15ed600153c4ff84b2d95abc2a79ff220ba77969812f5f562972651b902b5252c5a5e6325158f92e3c3c40b8894b7293b5b1ede830615b502dfe",
          "sha256": "e7dd4dd090f843d920138266b2fbe36ad4d2b68a8e7a33e493d9b097eb510a97",
          "sha1": "30c6b6149ae8ca95f2eae9022b971f30eda1e232",
          "md5": "81ad7fb0271356508d8652667e817313"
        }
      ]
    }
  ]
}
